ruuid4-0.1.5.dist-info/METADATA
ruuid4-0.1.5.dist-info/WHEEL
ruuid4-0.1.5.dist-info/licenses/LICENSE
ruuid4/__init__.py
ruuid4/__init__.pyi
ruuid4/py.typed
ruuid4/ruuid4.cpython-310-s390x-linux-gnu.so
ruuid4-0.1.5.dist-info/RECORD
