Metadata-Version: 2.4
Name: ruuid4
Version: 0.1.5
Classifier: Programming Language :: Rust
Classifier: Programming Language :: Python :: Implementation :: CPython
Classifier: Programming Language :: Python :: Implementation :: PyPy
License-File: LICENSE
Summary: A tiny, fast UUID4 generator powered by Rust.
License-Expression: MIT
Requires-Python: >=3.8
